Tigrina_alphabets/Tigrinya_alphabet_coder_decoder.py
Tigrina_alphabets/__init__.py
Tigrina_alphabets/adjectives.py
Tigrina_alphabets/alphabets.py
Tigrina_alphabets/code_decode.py
Tigrina_alphabets/data_process.py
Tigrina_alphabets/nouns.py
Tigrina_alphabets/test.py
Tigrina_alphabets/verb_to_be.py
Tigrina_alphabets/verbs.py
Tigrinya_alphabets-0.1.0.dist-info/METADATA
Tigrinya_alphabets-0.1.0.dist-info/WHEEL
Tigrinya_alphabets-0.1.0.dist-info/entry_points.txt
Tigrinya_alphabets-0.1.0.dist-info/top_level.txt
Tigrinya_alphabets-0.1.0.dist-info/RECORD
