Metadata-Version: 2.1
Name: Tigrinya-alphabets
Version: 0.1.0
Summary: A library for encoding and decoding Tigrinya alphabets
Home-page: UNKNOWN
Author: Gide Segid
Author-email: gidesegid@gmail.com
License: UNKNOWN
Platform: UNKNOWN
Classifier: Programming Language :: Python :: 3
Classifier: License :: OSI Approved :: MIT License
Classifier: Operating System :: OS Independent
